{
  "entities": [
    {
      "name": "sight",
      "type": "PERSON",
      "metadata": {},
      "salience": 0.5880521,
      "mentions": [
        {
          "text": {
            "content": "sight",
            "beginOffset": 213
          },
          "type": "COMMON"
        }
      ]
    },
    {
      "name": "guys",
      "type": "PERSON",
      "metadata": {},
      "salience": 0.07531474,
      "mentions": [
        {
          "text": {
            "content": "guys",
            "beginOffset": 5
          },
          "type": "COMMON"
        }
      ]
    },
    {
      "name": "love",
      "type": "OTHER",
      "metadata": {},
      "salience": 0.07177426,
      "mentions": [
        {
          "text": {
            "content": "love",
            "beginOffset": 18
          },
          "type": "COMMON"
        }
      ]
    },
    {
      "name": "girl",
      "type": "PERSON",
      "metadata": {},
      "salience": 0.07177426,
      "mentions": [
        {
          "text": {
            "content": "girl",
            "beginOffset": 32
          },
          "type": "COMMON"
        }
      ]
    },
    {
      "name": "heart",
      "type": "OTHER",
      "metadata": {},
      "salience": 0.03972306,
      "mentions": [
        {
          "text": {
            "content": "heart",
            "beginOffset": 98
          },
          "type": "COMMON"
        }
      ]
    },
    {
      "name": "heart",
      "type": "OTHER",
      "metadata": {},
      "salience": 0.02188045,
      "mentions": [
        {
          "text": {
            "content": "heart",
            "beginOffset": 146
          },
          "type": "COMMON"
        }
      ]
    },
    {
      "name": "ground",
      "type": "LOCATION",
      "metadata": {},
      "salience": 0.019177541,
      "mentions": [
        {
          "text": {
            "content": "ground",
            "beginOffset": 168
          },
          "type": "COMMON"
        }
      ]
    },
    {
      "name": "town",
      "type": "LOCATION",
      "metadata": {},
      "salience": 0.019177541,
      "mentions": [
        {
          "text": {
            "content": "town",
            "beginOffset": 222
          },
          "type": "COMMON"
        }
      ]
    },
    {
      "name": "double trouble",
      "type": "OTHER",
      "metadata": {},
      "salience": 0.017794006,
      "mentions": [
        {
          "text": {
            "content": "double trouble",
            "beginOffset": 239
          },
          "type": "COMMON"
        }
      ]
    },
    {
      "name": "trouble",
      "type": "OTHER",
      "metadata": {},
      "salience": 0.017794006,
      "mentions": [
        {
          "text": {
            "content": "trouble",
            "beginOffset": 268
          },
          "type": "COMMON"
        }
      ]
    },
    {
      "name": "anybody",
      "type": "PERSON",
      "metadata": {},
      "salience": 0.01756759,
      "mentions": [
        {
          "text": {
            "content": "anybody",
            "beginOffset": 316
          },
          "type": "COMMON"
        }
      ]
    },
    {
      "name": "trouble",
      "type": "OTHER",
      "metadata": {},
      "salience": 0.016298862,
      "mentions": [
        {
          "text": {
            "content": "trouble",
            "beginOffset": 291
          },
          "type": "COMMON"
        }
      ]
    },
    {
      "name": "matchbox",
      "type": "OTHER",
      "metadata": {},
      "salience": 0.0062801912,
      "mentions": [
        {
          "text": {
            "content": "matchbox",
            "beginOffset": 431
          },
          "type": "COMMON"
        }
      ]
    },
    {
      "name": "sea",
      "type": "LOCATION",
      "metadata": {},
      "salience": 0.0062801912,
      "mentions": [
        {
          "text": {
            "content": "sea",
            "beginOffset": 447
          },
          "type": "COMMON"
        }
      ]
    },
    {
      "name": "cards",
      "type": "OTHER",
      "metadata": {},
      "salience": 0.004352589,
      "mentions": [
        {
          "text": {
            "content": "cards",
            "beginOffset": 518
          },
          "type": "COMMON"
        }
      ]
    },
    {
      "name": "clouds",
      "type": "OTHER",
      "metadata": {},
      "salience": 0.0033793137,
      "mentions": [
        {
          "text": {
            "content": "clouds",
            "beginOffset": 377
          },
          "type": "COMMON"
        }
      ]
    },
    {
      "name": "grade",
      "type": "OTHER",
      "metadata": {},
      "salience": 0.0033793137,
      "mentions": [
        {
          "text": {
            "content": "grade",
            "beginOffset": 558
          },
          "type": "COMMON"
        }
      ]
    }
  ],
  "language": "en"
}
