{
  "entities": [
    {
      "name": "eyes",
      "type": "OTHER",
      "metadata": {},
      "salience": 0.32155183,
      "mentions": [
        {
          "text": {
            "content": "eyes",
            "beginOffset": 19
          },
          "type": "COMMON"
        }
      ]
    },
    {
      "name": "heart",
      "type": "OTHER",
      "metadata": {},
      "salience": 0.13367888,
      "mentions": [
        {
          "text": {
            "content": "heart",
            "beginOffset": 158
          },
          "type": "COMMON"
        }
      ]
    },
    {
      "name": "hands",
      "type": "OTHER",
      "metadata": {},
      "salience": 0.12554933,
      "mentions": [
        {
          "text": {
            "content": "hands",
            "beginOffset": 86
          },
          "type": "COMMON"
        }
      ]
    },
    {
      "name": "life",
      "type": "OTHER",
      "metadata": {},
      "salience": 0.11078447,
      "mentions": [
        {
          "text": {
            "content": "life",
            "beginOffset": 275
          },
          "type": "COMMON"
        }
      ]
    },
    {
      "name": "mind",
      "type": "OTHER",
      "metadata": {},
      "salience": 0.09181794,
      "mentions": [
        {
          "text": {
            "content": "mind",
            "beginOffset": 217
          },
          "type": "COMMON"
        }
      ]
    },
    {
      "name": "heart",
      "type": "OTHER",
      "metadata": {},
      "salience": 0.08304217,
      "mentions": [
        {
          "text": {
            "content": "heart",
            "beginOffset": 417
          },
          "type": "COMMON"
        }
      ]
    },
    {
      "name": "heart",
      "type": "OTHER",
      "metadata": {},
      "salience": 0.062177937,
      "mentions": [
        {
          "text": {
            "content": "heart",
            "beginOffset": 557
          },
          "type": "COMMON"
        }
      ]
    },
    {
      "name": "mind",
      "type": "OTHER",
      "metadata": {},
      "salience": 0.043681223,
      "mentions": [
        {
          "text": {
            "content": "mind",
            "beginOffset": 616
          },
          "type": "COMMON"
        }
      ]
    },
    {
      "name": "mind",
      "type": "OTHER",
      "metadata": {},
      "salience": 0.027716229,
      "mentions": [
        {
          "text": {
            "content": "mind",
            "beginOffset": 476
          },
          "type": "COMMON"
        }
      ]
    }
  ],
  "language": "en"
}
